cnb_api/__init__.py
cnb_api/api_client.py
cnb_api/api_response.py
cnb_api/configuration.py
cnb_api/exceptions.py
cnb_api/py.typed
cnb_api/rest.py
cnb_api/api/__init__.py
cnb_api/api/artifactory_api.py
cnb_api/api/assets_api.py
cnb_api/api/build_api.py
cnb_api/api/collaborators_api.py
cnb_api/api/contributors_api.py
cnb_api/api/followers_api.py
cnb_api/api/git_api.py
cnb_api/api/git_settings_api.py
cnb_api/api/issues_api.py
cnb_api/api/missions_api.py
cnb_api/api/organizations_api.py
cnb_api/api/pulls_api.py
cnb_api/api/releases_api.py
cnb_api/api/repo_contributor_api.py
cnb_api/api/repo_labels_api.py
cnb_api/api/repositories_api.py
cnb_api/api/starring_api.py
cnb_api/api/users_api.py
cnb_api/api/workspace_api.py
cnb_api/models/__init__.py
cnb_api/models/api_blob.py
cnb_api/models/api_branch.py
cnb_api/models/api_branch_commit.py
cnb_api/models/api_branch_detail.py
cnb_api/models/api_branch_protection.py
cnb_api/models/api_commit.py
cnb_api/models/api_commit_asset.py
cnb_api/models/api_commit_diff_file_patch.py
cnb_api/models/api_commit_object.py
cnb_api/models/api_commit_object_tree.py
cnb_api/models/api_commit_object_verification.py
cnb_api/models/api_commit_parent.py
cnb_api/models/api_commit_status.py
cnb_api/models/api_compare_response.py
cnb_api/models/api_content.py
cnb_api/models/api_issue.py
cnb_api/models/api_issue_comment.py
cnb_api/models/api_issue_detail.py
cnb_api/models/api_label.py
cnb_api/models/api_merge_pull_request.py
cnb_api/models/api_merge_pull_response.py
cnb_api/models/api_patch_issue_comment_form.py
cnb_api/models/api_patch_issue_form.py
cnb_api/models/api_patch_label_form.py
cnb_api/models/api_patch_pull_request.py
cnb_api/models/api_pipeline_settings.py
cnb_api/models/api_post_blob_form.py
cnb_api/models/api_post_issue_comment_form.py
cnb_api/models/api_post_issue_form.py
cnb_api/models/api_post_issue_labels_form.py
cnb_api/models/api_post_label_form.py
cnb_api/models/api_post_pull_labels_form.py
cnb_api/models/api_post_tag_from.py
cnb_api-0.0.1.dist-info/METADATA
cnb_api-0.0.1.dist-info/WHEEL
cnb_api-0.0.1.dist-info/top_level.txt
cnb_api-0.0.1.dist-info/RECORD
