Metadata-Version: 2.4
Name: cnb-api
Version: 0.0.1
Summary: CNB OPENAPI
Home-page: 
Author: Open API Support
Author-email: cnb@tencent.com
Keywords: OpenAPI,OpenAPI-Generator,CNB OPENAPI
Requires-Dist: urllib3<3.0.0,>=1.25.3
Requires-Dist: python-dateutil>=2.8.2
Requires-Dist: pydantic>=2
Requires-Dist: typing-extensions>=4.7.1
Dynamic: author
Dynamic: author-email
Dynamic: description
Dynamic: description-content-type
Dynamic: keywords
Dynamic: requires-dist
Dynamic: summary
